{
    "chapter_id": 10,
    "chapter_number": 10,
    "externalId": 411,
    "id": 411,
    "text": "यच्चापि सर्वभूतानां बीजं तदहमर्जुन।\n\nन तदस्ति विना यत्स्यान्मया भूतं चराचरम्।।10.39।।\n ",
    "title": "Verse 411",
    "verse_number": 39,
    "verse_order": 411,
    "transliteration": "yach chāpi sarva-bhūtānāṁ bījaṁ tad aham arjuna\nna tad asti vinā yat syān mayā bhūtaṁ charācharam\n",
    "word_meanings": "yat—which; cha—and; api—also; sarva-bhūtānām—of all living beings; bījam—generating seed; tat—that; aham—I; arjuna—Arjun; na—not; tat—that; asti—is; vinā—without; yat—which; syāt—may exist; mayā—me; bhūtam—creature; chara-acharam—moving and nonmoving\n"
}