{
    "chapter_id": 18,
    "chapter_number": 18,
    "externalId": 654,
    "id": 654,
    "text": "यया धर्ममधर्मं च कार्यं चाकार्यमेव च।अयथावत्प्रजानाति बुद्धिः सा पार्थ राजसी।।18.31।।",
    "title": "Verse 654",
    "verse_number": 31,
    "verse_order": 654,
    "transliteration": "yayā dharmam adharmaṁ cha kāryaṁ chākāryam eva cha\nayathāvat prajānāti buddhiḥ sā pārtha rājasī\n",
    "word_meanings": "yayā—by which; dharmam—righteousness; adharmam—unrighteousness; cha—and; kāryam—right conduct; cha—and; akāryam—wrong conduct; eva—certainly; cha—and; ayathā-vat—confused; prajānāti—distinguish; buddhiḥ—intellect; sā—that; pārtha—Arjun, the son of Pritha; rājasī—in the mode of passion\n"
}