{
    "chapter_id": 18,
    "chapter_number": 18,
    "externalId": 658,
    "id": 658,
    "text": "यया स्वप्नं भयं शोकं विषादं मदमेव च।न विमुञ्चति दुर्मेधा धृतिः सा पार्थ तामसी।।18.35।।",
    "title": "Verse 658",
    "verse_number": 35,
    "verse_order": 658,
    "transliteration": "yayā svapnaṁ bhayaṁ śhokaṁ viṣhādaṁ madam eva cha\nna vimuñchati durmedhā dhṛitiḥ sā pārtha tāmasī\n",
    "word_meanings": "yayā—in which; svapnam—dreaming; bhayam—fearing; śhokam—grieving; viṣhādam—despair; madam—conceit; eva—indeed; cha—and; na—not; vimuñchati—give up; durmedhā—unintelligent; dhṛitiḥ—resolve; sā—that; pārtha—Arjun, the son of Pritha; tāmasī—in the mode of ignorance\n"
}