{
    "chapter_id": 16,
    "chapter_number": 16,
    "externalId": 581,
    "id": 581,
    "text": "काममाश्रित्य दुष्पूरं दम्भमानमदान्विताः।मोहाद्गृहीत्वासद्ग्राहान्प्रवर्तन्तेऽशुचिव्रताः।।16.10।।",
    "title": "Verse 581",
    "verse_number": 10,
    "verse_order": 581,
    "transliteration": "kāmam āśhritya duṣhpūraṁ dambha-māna-madānvitāḥ\nmohād gṛihītvāsad-grāhān pravartante ’śhuchi-vratāḥ\n",
    "word_meanings": "kāmam—lust; āśhritya—harboring; duṣhpūram—insatiable; dambha—hypocrisy; māna—arrogance; mada-anvitāḥ—clinging to false tenets; mohāt—the illusioned; gṛihītvā—being attracted to; asat—impermanent; grāhān—things; pravartante—they flourish; aśhuchi-vratāḥ—with impure resolve\n"
}