{
    "chapter_id": 8,
    "chapter_number": 8,
    "externalId": 328,
    "id": 328,
    "text": "अव्यक्ताद्व्यक्तयः सर्वाः प्रभवन्त्यहरागमे।\n\nरात्र्यागमे प्रलीयन्ते तत्रैवाव्यक्तसंज्ञके।।8.18।।\n ",
    "title": "Verse 328",
    "verse_number": 18,
    "verse_order": 328,
    "transliteration": "avyaktād vyaktayaḥ sarvāḥ prabhavantyahar-āgame\nrātryāgame pralīyante tatraivāvyakta-sanjñake\n",
    "word_meanings": "avyaktāt—from the unmanifested; vyaktayaḥ—the manifested; sarvāḥ—all; prabhavanti—emanate; ahaḥ-āgame—at the advent of Brahma’s day; rātri-āgame—at the fall of Brahma’s night; pralīyante—they dissolve; tatra—into that; eva—certainly; avyakta-sanjñake—in that which is called the unmanifest\n"
}