{
    "chapter_id": 2,
    "chapter_number": 2,
    "externalId": 78,
    "id": 78,
    "text": "स्वधर्ममपि चावेक्ष्य न विकम्पितुमर्हसि।\n\nधर्म्याद्धि युद्धाछ्रेयोऽन्यत्क्षत्रियस्य न विद्यते।।2.31।।\n ",
    "title": "Verse 78",
    "verse_number": 31,
    "verse_order": 78,
    "transliteration": "swa-dharmam api chāvekṣhya na vikampitum arhasi\ndharmyāddhi yuddhāch chhreyo ’nyat kṣhatriyasya na vidyate\n",
    "word_meanings": "swa-dharmam—one’s duty in accordance with the Vedas; api—also; cha—and; avekṣhya—considering; na—not; vikampitum—to waver; arhasi—should; dharmyāt—for righteousness; hi—indeed; yuddhāt—than fighting; śhreyaḥ—better; anyat—another; kṣhatriyasya—of a warrior; na—not; vidyate—exists\n"
}