{
    "chapter_id": 1,
    "chapter_number": 1,
    "externalId": 26,
    "id": 26,
    "text": "तत्रापश्यत्स्थितान्पार्थः पितृ़नथ पितामहान्।\n\nआचार्यान्मातुलान्भ्रातृ़न्पुत्रान्पौत्रान्सखींस्तथा।।1.26।।\n ",
    "title": "Verse 26",
    "verse_number": 26,
    "verse_order": 26,
    "transliteration": "tatrāpaśhyat sthitān pārthaḥ pitṝīn atha pitāmahān\nāchāryān mātulān bhrātṝīn putrān pautrān sakhīṁs tathā\nśhvaśhurān suhṛidaśh chaiva senayor ubhayor api\n",
    "word_meanings": "tatra—there; apaśhyat—saw; sthitān—stationed; pārthaḥ—Arjun; pitṝīn—fathers; atha—thereafter; pitāmahān—grandfathers; āchāryān—teachers; mātulān—maternal uncles; bhrātṝīn—brothers; putrān—sons; pautrān—grandsons; sakhīn—friends; tathā—also; śhvaśhurān—fathers-in-law; suhṛidaḥ—well-wishers; cha—and; eva—indeed; senayoḥ—armies; ubhayoḥ—in both armies; api—also\n"
}